http_client_pretty_headers/__init__.py
http_client_pretty_headers/_version.py
http_client_pretty_headers-0.1.0.dist-info/METADATA
http_client_pretty_headers-0.1.0.dist-info/WHEEL
http_client_pretty_headers-0.1.0.dist-info/licenses/LICENSE.txt
http_client_pretty_headers-0.1.0.dist-info/RECORD
