Metadata-Version: 2.3
Name: http_client_pretty_headers
Version: 0.1.0
Summary: Display headers of HTTP protocol client in a readable way
Project-URL: Homepage, https://github.com/pbabinca/http_client_pretty_headers
Project-URL: Documentation, https://http-client-pretty-headers.readthedocs.io/
Project-URL: Bug Tracker, https://github.com/pbabinca/http_client_pretty_headers/issues
Project-URL: Changelog, https://github.com/pbabinca/http_client_pretty_headers/blob/main/CHANGELOG.md
Author-email: Pavol Babinčák <pbabinca@redhat.com>
License: MIT
License-File: LICENSE.txt
Classifier: Intended Audience :: Developers
Classifier: License :: OSI Approved :: MIT License
Classifier: Programming Language :: Python :: 3.9
Classifier: Programming Language :: Python :: 3.10
Classifier: Programming Language :: Python :: 3.11
Classifier: Programming Language :: Python :: 3.12
Classifier: Programming Language :: Python :: 3.13
Classifier: Topic :: Software Development :: Libraries :: Python Modules
Requires-Python: >=3.9
